<oai_dc:dc xmlns:oai_dc="http://www.openarchives.org/OAI/2.0/oai_dc/" xmlns:dc="http://purl.org/dc/elements/1.1/" xsi:schemaLocation="http://www.openarchives.org/OAI/2.0/oai_dc/  http://www.openarchives.org/OAI/2.0/oai_dc.xsd"  xmlns:xsi="http://www.w3.org/2001/XMLSchema-instance"><id>14403</id><datestamp>2021-06-29</datestamp><setSpec>DDC:1:10:100</setSpec>
          <dc:title xml:lang="de">Forschungsgrundlagen Wilhelm Windelband&lt;br /&gt;&lt;br /&gt;Windelband an Heinrich Rickert, Heidelberg, 14.1.1904, 4 S., hs. (lat. Schrift), UB Heidelberg, http://digi.ub.uni-heidelberg.de/diglit/heidhs2740IIIA-224_45</dc:title>
          <dc:creator>Bohr, Jörn</dc:creator>
          <dc:creator>Hartung, Gerald</dc:creator>
          <dc:creator>Bülow, Gilles</dc:creator>
          <dc:creator>Schlupkothen, Frederik</dc:creator>
          <dc:date>2021-06-21</dc:date>
          <dc:identifier>http://elpub.bib.uni-wuppertal.de/edocs/dokumente/edition/ww2020/0403</dc:identifier>
          <dc:identifier>http://elpub.bib.uni-wuppertal.de/servlets/DocumentServlet?id=14403</dc:identifier>
          <dc:identifier>urn:nbn:de:hbz:468-edww2020-000403-4</dc:identifier>
          <dc:identifier>http://elpub.bib.uni-wuppertal.de/servlets/DerivateServlet/Derivate-13403/</dc:identifier>
          <dc:description xml:lang="de">&lt;div xmlns="http://www.w3.org/1999/xhtml" style="font-family: serif; line-height: 1.2em; margin-bottom: 5em;" class="ED-TEI"&gt;&lt;p style="font-size: 1.1em; font-family: serif; font-style: italic; font-weight: normal; margin: 2em 0em 1em;" class="ED-titleStmt"&gt;Windelband an &lt;span class="ED-persName-received"&gt;Heinrich Rickert&lt;/span&gt;, &lt;span class="ED-location-sent"&gt;Heidelberg&lt;/span&gt;, &lt;span class="ED-date"&gt;14.1.1904&lt;/span&gt;, &lt;span class="ED-note"&gt;4 S., hs. (lat. Schrift)&lt;/span&gt;, &lt;span class="ED-pubPlace"&gt;UB Heidelberg, &lt;/span&gt;&lt;span class="ED-link"&gt;&lt;a href="http://digi.ub.uni-heidelberg.de/diglit/heidhs2740IIIA-224_45"&gt;http://digi.ub.uni-heidelberg.de/diglit/heidhs2740IIIA-224_45&lt;/a&gt;&lt;/span&gt;&lt;/p&gt;&lt;div style="border: 1px solid LightGray; padding: 1em;" class="ED-text"&gt;&lt;p style="text-align: right; margin: 0em; margin-top: 1em;" class="ED-dateline"&gt;Heidelberg, 14.1.04.&lt;/p&gt;&lt;p style="text-indent: 0em; margin: 0em; margin-top: 1em;" class="ED-salute"&gt;Lieber, werter Herr College,&lt;/p&gt;&lt;p style="text-indent: 0em; margin: 0em; margin-top: 1em;" class="ED-p"&gt;Zu meiner grossen Freude höre ich von meiner Frau, dich sich z&lt;span style="color: Gray;" class="ED-add"&gt;[ur]&lt;/span&gt; Z&lt;span style="color: Gray;" class="ED-add"&gt;[eit]&lt;/span&gt; in Freiburg befindet und mich mit Nachrichten über Ihre Geschicke versehen hat, dass es jetzt Ihnen und ebenso Ihrer Frau Gemahlin und dem &lt;span style="text-decoration: underline dotted;" class="ED-text-lem" itemref="app-editorial-1" title="jungen Weltbürger ] Rickerts Sohn Franz Rickert (1904–1991), Gold- u. Silberschmied, Prof. an der Akademie der Bildenden Künste München (NDB)."&gt;jungen Weltbürger&lt;/span&gt;&lt;a style="font-style: normal; vertical-align: super; font-size: 80%; line-height: 100%;" class="ED-anchor" href="#app-editorial-1" id="app-editorial-1-ref" title="jungen Weltbürger ] Rickerts Sohn Franz Rickert (1904–1991), Gold- u. Silberschmied, Prof. an der Akademie der Bildenden Künste München (NDB)."&gt;[1]&lt;/a&gt; entschieden gut geht. Das ist eine grosse Beruhigung für mich, und damit fällt mir eine Sorge von der Seele, die mich in dieser Zeit schwer bedrückt hat. ich habe den herzlichen Anteil an Ihrem Leiden und an der &lt;span style="text-decoration: underline dotted;" class="ED-text-lem" itemref="app-editorial-2" title="unglücklichen Complication ] Rickert war im Januar 1904 an einer Blinddarmentzündung erkrankt, die im Februar operiert wurde, so daß er erst im SS 1904 seiner Lehrverpflichtung wieder nachkommen konnte (UA Freiburg, B 38/283, Wiederbesetzung des Lehrstuhls für Philosophie 1886–1913, Schreiben Rickerts vom 18.1., 29.1. u. 22.2.1904; vgl. Hermann Glockner: Heidelberger Bilderbuch. Erinnerungen. Bonn: Bouvier 1969, S. 17)."&gt;unglücklichen Complication&lt;/span&gt;&lt;a style="font-style: normal; vertical-align: super; font-size: 80%; line-height: 100%;" class="ED-anchor" href="#app-editorial-2" id="app-editorial-2-ref" title="unglücklichen Complication ] Rickert war im Januar 1904 an einer Blinddarmentzündung erkrankt, die im Februar operiert wurde, so daß er erst im SS 1904 seiner Lehrverpflichtung wieder nachkommen konnte (UA Freiburg, B 38/283, Wiederbesetzung des Lehrstuhls für Philosophie 1886–1913, Schreiben Rickerts vom 18.1., 29.1. u. 22.2.1904; vgl. Hermann Glockner: Heidelberger Bilderbuch. Erinnerungen. Bonn: Bouvier 1969, S. 17)."&gt;[2]&lt;/a&gt; genommen, die es in so akute Beziehung zu den kritischen Tagen in dem Zustande Ihrer Frau Gemahlin brachte. Möchte nun Alles gut weitergehen, Sie eine schnelle und gründliche &lt;span style="color: Gray;" class="ED-pb"&gt;|&lt;/span&gt; Reconvalescenz, Ihre Frau Gemahlin baldige Erholung und Ihr jüngster Sohn eine glückliche Entwicklung finden! ich wünsche es von ganzem Herzen!&lt;/p&gt;&lt;p style="text-indent: 1em; margin: 0em;" class="ED-p"&gt;Eben habe ich &lt;span style="text-decoration: underline dotted;" class="ED-text-lem" itemref="app-editorial-3" title="Ferdinand Schmidtʼs Dissertation über Fichte ] gemeint: Friedrich Alfred Schmid [Noerr] (1877–1969, zum Namenszusatz als Schriftsteller (nach einer Konditorei in Schmids Verwandschaft) vgl. Hermann Glockner: Heidelberger Bilderbuch. Erinnerungen. Bonn: Bouvier 1969, S. 50) mit dessen Freiburger Dissertation über Die Philosophie Fichtes mit Rücksicht auf die Frage nach der „Veränderten Lehre“, 1904 (im Buchhandel als: Fichtes Philosophie und das Problem ihrer inneren Einheit. (Die Frage nach der veränderten Lehre). Freiburg i. B.: Ragoczy 1904; beide im Umfang von 112 S.). 1905 in Heidelberg habilitiert, dort bis 1917 PD (1910–1917 a. o. Prof. für Philosophie und Ästhetik), danach freier Schriftsteller (Universität Heidelberg, Adreßbücher und Vorlesungsverzeichnisse: http://www.ub.uni-heidelberg.de/helios/digi/quellenunihd.html; Wikipedia 10.4.2017)."&gt;Ferdinand Schmidtʼs Dissertation über &lt;/span&gt;&lt;span class="ED-name"&gt;&lt;span style="text-decoration: underline dotted;" class="ED-text-lem" itemref="app-editorial-3" title="Ferdinand Schmidtʼs Dissertation über Fichte ] gemeint: Friedrich Alfred Schmid [Noerr] (1877–1969, zum Namenszusatz als Schriftsteller (nach einer Konditorei in Schmids Verwandschaft) vgl. Hermann Glockner: Heidelberger Bilderbuch. Erinnerungen. Bonn: Bouvier 1969, S. 50) mit dessen Freiburger Dissertation über Die Philosophie Fichtes mit Rücksicht auf die Frage nach der „Veränderten Lehre“, 1904 (im Buchhandel als: Fichtes Philosophie und das Problem ihrer inneren Einheit. (Die Frage nach der veränderten Lehre). Freiburg i. B.: Ragoczy 1904; beide im Umfang von 112 S.). 1905 in Heidelberg habilitiert, dort bis 1917 PD (1910–1917 a. o. Prof. für Philosophie und Ästhetik), danach freier Schriftsteller (Universität Heidelberg, Adreßbücher und Vorlesungsverzeichnisse: http://www.ub.uni-heidelberg.de/helios/digi/quellenunihd.html; Wikipedia 10.4.2017)."&gt;Fichte&lt;/span&gt;&lt;/span&gt;&lt;span class="ED-name"&gt;&lt;a style="font-style: normal; vertical-align: super; font-size: 80%; line-height: 100%;" class="ED-anchor" href="#app-editorial-3" id="app-editorial-3-ref" title="Ferdinand Schmidtʼs Dissertation über Fichte ] gemeint: Friedrich Alfred Schmid [Noerr] (1877–1969, zum Namenszusatz als Schriftsteller (nach einer Konditorei in Schmids Verwandschaft) vgl. Hermann Glockner: Heidelberger Bilderbuch. Erinnerungen. Bonn: Bouvier 1969, S. 50) mit dessen Freiburger Dissertation über Die Philosophie Fichtes mit Rücksicht auf die Frage nach der „Veränderten Lehre“, 1904 (im Buchhandel als: Fichtes Philosophie und das Problem ihrer inneren Einheit. (Die Frage nach der veränderten Lehre). Freiburg i. B.: Ragoczy 1904; beide im Umfang von 112 S.). 1905 in Heidelberg habilitiert, dort bis 1917 PD (1910–1917 a. o. Prof. für Philosophie und Ästhetik), danach freier Schriftsteller (Universität Heidelberg, Adreßbücher und Vorlesungsverzeichnisse: http://www.ub.uni-heidelberg.de/helios/digi/quellenunihd.html; Wikipedia 10.4.2017)."&gt;[3]&lt;/a&gt;&lt;/span&gt; erhalten und mit grossem Interesse angelesen: ich beglückwünsche Sie zu dem erfreulichen Kreise von Arbeiten, die aus Ihren Anregungen hervorgehen; ich verfolge jetzt diese zusammenhangenden Untersuchungen Ihres Seminars nicht ohne Neid. So günstig vielleicht im Verhältnis zu meiner sonst in diesen Semestern allerdings sehr gehäuften Arbeitslast der Ausfall oder die äusserste Beschränkung solcher Tätigkeit ist, so empfinde &lt;span style="color: Gray;" class="ED-pb"&gt;|&lt;/span&gt; ich es doch als einen ausgesprochenen Mangel, dass sie mir jetzt noch hier versagt ist, dass ich keinen regelmäßigen Zusammenhang mit den besseren Elementen der Zuhörerschaft, die ja auch hier vorhanden sind, habe, dass ich ihnen noch keine Arbeitsstätte zu bieten vermag, an der ich energisch auf sie einwirken kann. Das blosse Vorlesen halte ich nicht mehr aus, und ich muss bald Mittel und Wege finden, um über die starken persönlichen Schwierigkeiten hinaus zu &lt;span style="text-decoration: underline dotted;" class="ED-text-lem" itemref="app-editorial-4" title="dem mir zugesicherten Seminar ] vgl. Windelband an Franz Böhm vom 22.2.1904 ff."&gt;dem mir zugesicherten Seminar&lt;/span&gt;&lt;a style="font-style: normal; vertical-align: super; font-size: 80%; line-height: 100%;" class="ED-anchor" href="#app-editorial-4" id="app-editorial-4-ref" title="dem mir zugesicherten Seminar ] vgl. Windelband an Franz Böhm vom 22.2.1904 ff."&gt;[4]&lt;/a&gt; tatsächlich zu gelangen.&lt;/p&gt;&lt;p style="text-indent: 1em; margin: 0em;" class="ED-p"&gt;Wenn das Heft der Kantstudien zum 100&lt;sup style="vertical-align: super; font-size: 80%; line-height: 100%;"&gt;t&lt;/sup&gt; Todestage erscheint, hoffe ich Ihnen eine Art von programmatischen &lt;span style="text-decoration: underline dotted;" class="ED-text-lem" itemref="app-editorial-5" title="Artikel ] vgl. Windelband: Nach hundert Jahren. In: Kant-Studien 9 (1904), S. 5–20, sowie in: Zu Kants Gedächtnis. Zwölf Festgaben zu seinem 100jährigen Todestage. Hg. v. H. Vaihinger u. B. Bauch."&gt;Artikel&lt;/span&gt;&lt;a style="font-style: normal; vertical-align: super; font-size: 80%; line-height: 100%;" class="ED-anchor" href="#app-editorial-5" id="app-editorial-5-ref" title="Artikel ] vgl. Windelband: Nach hundert Jahren. In: Kant-Studien 9 (1904), S. 5–20, sowie in: Zu Kants Gedächtnis. Zwölf Festgaben zu seinem 100jährigen Todestage. Hg. v. H. Vaihinger u. B. Bauch."&gt;[5]&lt;/a&gt; zuzuschicken, auf dessen Aufnahme bei Ihnen ich sehr gespannt bin. Leider muss ich noch einen zweiten &lt;span style="text-decoration: underline dotted;" class="ED-text-lem" itemref="app-philological-1" title="Aufsatz ] so wörtlich"&gt;Aufsatz&lt;/span&gt;&lt;a style="font-style: normal; vertical-align: super; font-size: 80%; line-height: 100%;" class="ED-anchor" href="#app-philological-1" id="app-philological-1-ref" title="Aufsatz ] so wörtlich"&gt;[a]&lt;/a&gt; &lt;span style="color: Gray;" class="ED-pb"&gt;|&lt;/span&gt; über Kant bei diesem Anlass reden und vielleicht drucken lassen, da unsre Universität &lt;span style="text-decoration: underline dotted;" class="ED-text-lem" itemref="app-editorial-6" title="am 12 Februar ] abends 7 Uhr, zum 100. Todestag Kants, vgl. die Ankündigung in: Heidelberger Zeitung, Nr. 25 vom 30.1.1904, Erstes Blatt, S. 4."&gt;am 12 Febr&lt;/span&gt;&lt;span style="color: Gray;" class="ED-add"&gt;&lt;span style="text-decoration: underline dotted;" class="ED-text-lem" itemref="app-editorial-6" title="am 12 Februar ] abends 7 Uhr, zum 100. Todestag Kants, vgl. die Ankündigung in: Heidelberger Zeitung, Nr. 25 vom 30.1.1904, Erstes Blatt, S. 4."&gt;[uar]&lt;/span&gt;&lt;/span&gt;&lt;a style="font-style: normal; vertical-align: super; font-size: 80%; line-height: 100%;" class="ED-anchor" href="#app-editorial-6" id="app-editorial-6-ref" title="am 12 Februar ] abends 7 Uhr, zum 100. Todestag Kants, vgl. die Ankündigung in: Heidelberger Zeitung, Nr. 25 vom 30.1.1904, Erstes Blatt, S. 4."&gt;[6]&lt;/a&gt; einen Actus veranstaltet und die &lt;span style="text-decoration: underline dotted;" class="ED-text-lem" itemref="app-editorial-7" title="Festrede ] vgl. Windelband: Immanuel Kant und seine Weltanschauung. Gedenkrede zur Feier der 100. Wiederkehr seines Todestages, an der Universität Heidelberg. Heidelberg: C. Winter 1904.Berlin: Reuther &amp; Reichard 1904, S. 5–20."&gt;Festrede&lt;/span&gt;&lt;a style="font-style: normal; vertical-align: super; font-size: 80%; line-height: 100%;" class="ED-anchor" href="#app-editorial-7" id="app-editorial-7-ref" title="Festrede ] vgl. Windelband: Immanuel Kant und seine Weltanschauung. Gedenkrede zur Feier der 100. Wiederkehr seines Todestages, an der Universität Heidelberg. Heidelberg: C. Winter 1904.Berlin: Reuther &amp; Reichard 1904, S. 5–20."&gt;[7]&lt;/a&gt; mir zufällt, weil &lt;span class="ED-name"&gt;Kuno Fischer&lt;/span&gt;s Gesundheitszustand ihn ja leider völlig ausschliesst. Auch bei &lt;span class="ED-name"&gt;Zeller&lt;/span&gt;ʼs 90. Geburtstage am 22. Jan&lt;span style="color: Gray;" class="ED-add"&gt;[uar]&lt;/span&gt; werde ich &lt;span style="text-decoration: underline dotted;" class="ED-text-lem" itemref="app-editorial-8" title="unsre Universität in Stuttgart zu vertreten ] vgl. den Bericht in: Chronik der Stadt Heidelberg für das Jahr 1904. 12. Jg., im Auftrag des Stadtrates bearbeitet v. August Thorbecke. Heidelberg: I. Hörning 1906, S. 68: Als am 29. Januar Professor Dr. Ed. Zeller in Stuttgart seinen 90. Geburtstag feierte, überbrachte Geheimerat Dr. Windelband die Glückwünsche der Universität, deren Lehrer Zeller von 1862–1872 gewesen war; am 12. Februar, dem 100. Todestag Kants, feierte sie das Andenken an den großen Philosophen durch einen Festakt, bei dem Geheimerat Dr. Windelband die Festrede hielt. Die Stuttgarter Ansprache Windelbands ist abgedruckt in: Vom neunzigsten Geburtstag Eduard Zellers 22. Januar 1904. Als Manuscript gedruckt Stuttgart: Felix Krais 1904, S. 13–15: Exzellenz, ich komme im Namen von Heidelberg. Der engere Senat als Vertreter der Universität und die philosophische Fakultät haben mich gleichmäßig durch den Auftrag geehrt, Ihnen an diesem Tage, der seinesgleichen nicht in der gelehrten Welt hat, die ehrfurchtsvollsten Glückwünsche darzubringen. Das Jahrzehnt, das Sie in Ihrem an Arbeit und Erfolg reichen Leben unserer Universität gewidmet haben, steht bei uns in dankbarem Gedenken, wenn auch unter den jetzigen Mitgliedern der philosophischen Fakultät keiner mehr ist, der die Ehre hatte, mit Ew. Exzellenz zusammenwirken: unser Senior ist Ihr Nachfolger im Lehramt, Exzellenz Kuno Fischer. Er würde gewiß als Ihr treuer Verehrer und Freund am liebsten heute an dieser Stelle stehen, wenn ihn nicht die beklagenswerte Ungunst seines körperlichen Befindens daran hinderte, die ihn in diesem Semester auch gezwungen hat, auf sein Liebstes, die Lehrtätigkeit, zu verzichten. So ist es mir, der ich berufen sein werde, die Tradition der philosophischen Lehre an unserer Universität fortzusetzen, | die Sie, Exzellenz, geschaffen haben und die Kuno Fischer aufrecht erhalten hat – so ist es mir zugefallen, heute bei Ihnen unsre Universität zu vertreten; und ich weiß es meinen Herrn Kollegen innigen Dank, daß sie mir so die Gelegenheit gegeben haben, Ihnen auch persönlich die Gefühle auszudrücken, mit denen ich diesen Tag begrüße. Sie haben, Exzellenz, der Nestor der deutschen Philosophie, die Generationen kommen und gehen sehen. Sie sind erwachsen mit der Hochflut der idealistischen Spekulation und haben, als sie an den religiösen Fragen auseinander ging, in jungen Jahren Ihr gewichtiges Wort in den Streit geworfen. Sie haben dann über die Zeit der Ebbe des philosophischen Interesses, die auf so viel Ueberschwang folgen mußte, Ihr Schiff mit wertvollem Inhalt sicher gesteuert; in Hegels historischer Leistung fanden Sie den bleibenden Wert seines Wirkens, und die Kühnheiten seiner Konstruktion korrigierten Sie durch die bewundernswerte Weite und Breite Ihrer Gelehrsamkeit ebenso wie durch die strenge Sicherheit Ihres forschenden Wirklichkeitssinnes. An dem würdigsten Gegenstande, an der Philosophie, deren Schüler wir immer alle bleiben, bewährten Sie diese vorbildliche Kraft Ihres Geistes und schufen daraus das Werk, das monumentale, das mit Ihrem Namen die Zeiten überdauern wird. Allein niemals sind Sie der trüben Meinung gewesen, daß die Philosophie aufhören solle und nur ihre Geschichte übrig bleibe. Sie waren einer der Ersten, die zu der Besonnenheit des kritischen Philosophierens zurückriefen und einem philosophielosen Geschlechte lehrten, was Kant ihm wieder werden sollte. Aber auch dabei bewahrte Sie ihr historisches Verständnis und Ihr eignes fachliches Denken davor, bei der Aengstlichkeit der kantischen Erkenntnistheorie stehen zu bleiben, und so waren Sie es, der von Anfang an zur Arbeit an der objektiven Ausgestaltung seiner Lehre aufrief und führend anleitete, die in den letzten Jahrzehnten siegreich vorgedrungen ist. So sind wir alle historisch und systematisch Ihre Schüler und Sie genießen die Freude, alle Keime, die Sie ausgesät haben, als lebenskräftige Triebe sich entfalten zu sehen. Und so gestatten Sie auch mir, daß ich die Gunst des Tages, der mich | persönlich zu Ihnen führt, auszunutzen wage, um Ihnen auszusprechen, wie auch ich allzeit bewundernd zu Ihnen aufgeschaut habe und Ihrer Führung gefolgt bin. Mit meinen Kollegen, mit der ganzen wissenschaftlichen Welt preise ich die Gunst des Geschicks, das Sie uns in einer unvergleichlichen Rüstigkeit der geistigen Arbeit bis auf den heutigen Tag erhalten hat, und ich kann nichts besseres wünschen, als daß es Ihnen noch weiterhin lange gegeben sei, aus Ihrer schaffensreichen und gedankenvollen Muße heraus uns den Mitgenuß an den Früchten eines unermüdlichen Forschens zu gönnen. Der Wiederhall dessen, was Sie uns gelehrt haben und noch lehren, klingt allüberall: mögen Sie überzeugt sein, daß es nirgends freudiger aufgenommen und treuer bewahrt wird als in Heidelberg."&gt;unsre Universität in Stuttgart zu vertreten&lt;/span&gt;&lt;a style="font-style: normal; vertical-align: super; font-size: 80%; line-height: 100%;" class="ED-anchor" href="#app-editorial-8" id="app-editorial-8-ref" title="unsre Universität in Stuttgart zu vertreten ] vgl. den Bericht in: Chronik der Stadt Heidelberg für das Jahr 1904. 12. Jg., im Auftrag des Stadtrates bearbeitet v. August Thorbecke. Heidelberg: I. Hörning 1906, S. 68: Als am 29. Januar Professor Dr. Ed. Zeller in Stuttgart seinen 90. Geburtstag feierte, überbrachte Geheimerat Dr. Windelband die Glückwünsche der Universität, deren Lehrer Zeller von 1862–1872 gewesen war; am 12. Februar, dem 100. Todestag Kants, feierte sie das Andenken an den großen Philosophen durch einen Festakt, bei dem Geheimerat Dr. Windelband die Festrede hielt. Die Stuttgarter Ansprache Windelbands ist abgedruckt in: Vom neunzigsten Geburtstag Eduard Zellers 22. Januar 1904. Als Manuscript gedruckt Stuttgart: Felix Krais 1904, S. 13–15: Exzellenz, ich komme im Namen von Heidelberg. Der engere Senat als Vertreter der Universität und die philosophische Fakultät haben mich gleichmäßig durch den Auftrag geehrt, Ihnen an diesem Tage, der seinesgleichen nicht in der gelehrten Welt hat, die ehrfurchtsvollsten Glückwünsche darzubringen. Das Jahrzehnt, das Sie in Ihrem an Arbeit und Erfolg reichen Leben unserer Universität gewidmet haben, steht bei uns in dankbarem Gedenken, wenn auch unter den jetzigen Mitgliedern der philosophischen Fakultät keiner mehr ist, der die Ehre hatte, mit Ew. Exzellenz zusammenwirken: unser Senior ist Ihr Nachfolger im Lehramt, Exzellenz Kuno Fischer. Er würde gewiß als Ihr treuer Verehrer und Freund am liebsten heute an dieser Stelle stehen, wenn ihn nicht die beklagenswerte Ungunst seines körperlichen Befindens daran hinderte, die ihn in diesem Semester auch gezwungen hat, auf sein Liebstes, die Lehrtätigkeit, zu verzichten. So ist es mir, der ich berufen sein werde, die Tradition der philosophischen Lehre an unserer Universität fortzusetzen, | die Sie, Exzellenz, geschaffen haben und die Kuno Fischer aufrecht erhalten hat – so ist es mir zugefallen, heute bei Ihnen unsre Universität zu vertreten; und ich weiß es meinen Herrn Kollegen innigen Dank, daß sie mir so die Gelegenheit gegeben haben, Ihnen auch persönlich die Gefühle auszudrücken, mit denen ich diesen Tag begrüße. Sie haben, Exzellenz, der Nestor der deutschen Philosophie, die Generationen kommen und gehen sehen. Sie sind erwachsen mit der Hochflut der idealistischen Spekulation und haben, als sie an den religiösen Fragen auseinander ging, in jungen Jahren Ihr gewichtiges Wort in den Streit geworfen. Sie haben dann über die Zeit der Ebbe des philosophischen Interesses, die auf so viel Ueberschwang folgen mußte, Ihr Schiff mit wertvollem Inhalt sicher gesteuert; in Hegels historischer Leistung fanden Sie den bleibenden Wert seines Wirkens, und die Kühnheiten seiner Konstruktion korrigierten Sie durch die bewundernswerte Weite und Breite Ihrer Gelehrsamkeit ebenso wie durch die strenge Sicherheit Ihres forschenden Wirklichkeitssinnes. An dem würdigsten Gegenstande, an der Philosophie, deren Schüler wir immer alle bleiben, bewährten Sie diese vorbildliche Kraft Ihres Geistes und schufen daraus das Werk, das monumentale, das mit Ihrem Namen die Zeiten überdauern wird. Allein niemals sind Sie der trüben Meinung gewesen, daß die Philosophie aufhören solle und nur ihre Geschichte übrig bleibe. Sie waren einer der Ersten, die zu der Besonnenheit des kritischen Philosophierens zurückriefen und einem philosophielosen Geschlechte lehrten, was Kant ihm wieder werden sollte. Aber auch dabei bewahrte Sie ihr historisches Verständnis und Ihr eignes fachliches Denken davor, bei der Aengstlichkeit der kantischen Erkenntnistheorie stehen zu bleiben, und so waren Sie es, der von Anfang an zur Arbeit an der objektiven Ausgestaltung seiner Lehre aufrief und führend anleitete, die in den letzten Jahrzehnten siegreich vorgedrungen ist. So sind wir alle historisch und systematisch Ihre Schüler und Sie genießen die Freude, alle Keime, die Sie ausgesät haben, als lebenskräftige Triebe sich entfalten zu sehen. Und so gestatten Sie auch mir, daß ich die Gunst des Tages, der mich | persönlich zu Ihnen führt, auszunutzen wage, um Ihnen auszusprechen, wie auch ich allzeit bewundernd zu Ihnen aufgeschaut habe und Ihrer Führung gefolgt bin. Mit meinen Kollegen, mit der ganzen wissenschaftlichen Welt preise ich die Gunst des Geschicks, das Sie uns in einer unvergleichlichen Rüstigkeit der geistigen Arbeit bis auf den heutigen Tag erhalten hat, und ich kann nichts besseres wünschen, als daß es Ihnen noch weiterhin lange gegeben sei, aus Ihrer schaffensreichen und gedankenvollen Muße heraus uns den Mitgenuß an den Früchten eines unermüdlichen Forschens zu gönnen. Der Wiederhall dessen, was Sie uns gelehrt haben und noch lehren, klingt allüberall: mögen Sie überzeugt sein, daß es nirgends freudiger aufgenommen und treuer bewahrt wird als in Heidelberg."&gt;[8]&lt;/a&gt; haben.&lt;/p&gt;&lt;p style="text-indent: 1em; margin: 0em;" class="ED-p"&gt;Meine Arbeiten schreiten also langsamer fort, als ich wünschte und hoffte. Die &lt;span style="text-decoration: underline dotted;" class="ED-text-lem" itemref="app-editorial-9" title="Ausgabe der Urteilskraft ] vgl. Windelband an Wilhelm Dilthey vom 16.7.1902 sowie Windelband: Einleitung. Sachliche Erläuterungen. Lesarten [zur Kritik der Urteilskraft]. In: Kant’s Werke Bd. 5. Kritik der praktischen Vernunft. Hg. v. Paul Natorp. Kritik der Urtheilskraft. Hg. v. W. Windelband. Berlin: Georg Reimer 1908 (Kant’s Gesammelte Schriften. Hg. v. der Königlich Preußischen Akademie der Wissenschaften. Abt. 1, Bd. 5), S. 512–527, 527–530, 530–543. 2. Abdruck Berlin: Georg Reimer 1913."&gt;Ausgabe der Urteilskraft&lt;/span&gt;&lt;a style="font-style: normal; vertical-align: super; font-size: 80%; line-height: 100%;" class="ED-anchor" href="#app-editorial-9" id="app-editorial-9-ref" title="Ausgabe der Urteilskraft ] vgl. Windelband an Wilhelm Dilthey vom 16.7.1902 sowie Windelband: Einleitung. Sachliche Erläuterungen. Lesarten [zur Kritik der Urteilskraft]. In: Kant’s Werke Bd. 5. Kritik der praktischen Vernunft. Hg. v. Paul Natorp. Kritik der Urtheilskraft. Hg. v. W. Windelband. Berlin: Georg Reimer 1908 (Kant’s Gesammelte Schriften. Hg. v. der Königlich Preußischen Akademie der Wissenschaften. Abt. 1, Bd. 5), S. 512–527, 527–530, 530–543. 2. Abdruck Berlin: Georg Reimer 1913."&gt;[9]&lt;/a&gt; ist mir recht eine Kugel ans Bein; ich wolltʼ ich hättʼs abgelehnt.&lt;/p&gt;&lt;p style="text-indent: 1em; margin: 0em;" class="ED-p"&gt;Nun nochmals mit allen guten Wünschen und herzlichen Grüssen der Ihrige&lt;/p&gt;&lt;p style="text-indent: 0em; margin: 0em; margin-top: 1em;" class="ED-signed"&gt;W Windelband&lt;/p&gt;&lt;/div&gt;&lt;h2 style="font-size: 1.1em; font-family: serif; font-style: italic; font-weight: normal; margin: 2em 0em 1em;" class="ED-app-title"&gt;Anmerkungen zum Textbefund&lt;/h2&gt;&lt;div style="position: relative; margin: .3em 0em; margin-left: 2.5em; font-style: italic;" class="ED-app-philological" id="app-philological-1"&gt;&lt;span style="left: -2.5em; position: absolute; text-indent: 0em; font-style: normal;" class="ED-app-num"&gt;a&lt;/span&gt;&lt;a style="left: -.8em; position: absolute; text-indent: 0em; font-style: normal;" href="#app-philological-1-ref" class="ED-app-corresp" title="back to content"&gt;↑&lt;/a&gt;&lt;span style="font-style: normal;" class="ED-lem"&gt;Aufsatz&lt;/span&gt;&lt;span style="font-style: normal;" class="ED-lem-sep"&gt; ] &lt;/span&gt;so wörtlich&lt;/div&gt;&lt;h2 style="font-size: 1.1em; font-family: serif; font-style: italic; font-weight: normal; margin: 2em 0em 1em;" class="ED-app-title"&gt;Anmerkungen der Herausgeber&lt;/h2&gt;&lt;div style="position: relative; margin: .3em 0em; margin-left: 2.5em; font-style: italic;" class="ED-app-editorial" id="app-editorial-1"&gt;&lt;span style="left: -2.5em; position: absolute; text-indent: 0em; font-style: normal;" class="ED-app-num"&gt;1&lt;/span&gt;&lt;a style="left: -.8em; position: absolute; text-indent: 0em; font-style: normal;" href="#app-editorial-1-ref" class="ED-app-corresp" title="back to content"&gt;↑&lt;/a&gt;&lt;span style="font-style: normal;" class="ED-lem"&gt;jungen Weltbürger&lt;/span&gt;&lt;span style="font-style: normal;" class="ED-lem-sep"&gt; ] &lt;/span&gt;Rickerts Sohn &lt;span class="ED-name"&gt;Franz Rickert&lt;/span&gt; (1904–1991), Gold- &lt;abbr title="und" class="ED-abbr"&gt;u.&lt;/abbr&gt; Silberschmied, &lt;abbr title="Professor" class="ED-abbr"&gt;Prof.&lt;/abbr&gt; an der Akademie der Bildenden Künste München (&lt;abbr title="Neue Deutsche Biographie" class="ED-abbr"&gt;NDB&lt;/abbr&gt;).&lt;/div&gt;&lt;div style="position: relative; margin: .3em 0em; margin-left: 2.5em; font-style: italic;" class="ED-app-editorial" id="app-editorial-2"&gt;&lt;span style="left: -2.5em; position: absolute; text-indent: 0em; font-style: normal;" class="ED-app-num"&gt;2&lt;/span&gt;&lt;a style="left: -.8em; position: absolute; text-indent: 0em; font-style: normal;" href="#app-editorial-2-ref" class="ED-app-corresp" title="back to content"&gt;↑&lt;/a&gt;&lt;span style="font-style: normal;" class="ED-lem"&gt;unglücklichen Complication&lt;/span&gt;&lt;span style="font-style: normal;" class="ED-lem-sep"&gt; ] &lt;/span&gt;&lt;span class="ED-name"&gt;Rickert&lt;/span&gt; war im Januar 1904 an einer Blinddarmentzündung erkrankt, die im Februar operiert wurde, so daß er erst im &lt;abbr title="Sommersemester" class="ED-abbr"&gt;SS&lt;/abbr&gt; 1904 seiner Lehrverpflichtung wieder nachkommen konnte (&lt;abbr title="Universitätsarchiv" class="ED-abbr"&gt;UA&lt;/abbr&gt; Freiburg, B 38/283, Wiederbesetzung des Lehrstuhls für Philosophie 1886–1913, Schreiben Rickerts vom 18.1., 29.1. &lt;abbr title="und" class="ED-abbr"&gt;u.&lt;/abbr&gt; 22.2.1904; &lt;abbr title="vergleiche" class="ED-abbr"&gt;vgl.&lt;/abbr&gt; Hermann Glockner: Heidelberger Bilderbuch. Erinnerungen. Bonn: Bouvier 1969, &lt;abbr title="Seite" class="ED-abbr"&gt;S.&lt;/abbr&gt; 17).&lt;/div&gt;&lt;div style="position: relative; margin: .3em 0em; margin-left: 2.5em; font-style: italic;" class="ED-app-editorial" id="app-editorial-3"&gt;&lt;span style="left: -2.5em; position: absolute; text-indent: 0em; font-style: normal;" class="ED-app-num"&gt;3&lt;/span&gt;&lt;a style="left: -.8em; position: absolute; text-indent: 0em; font-style: normal;" href="#app-editorial-3-ref" class="ED-app-corresp" title="back to content"&gt;↑&lt;/a&gt;&lt;span style="font-style: normal;" class="ED-lem"&gt;Ferdinand Schmidtʼs Dissertation über &lt;span class="ED-name"&gt;Fichte&lt;/span&gt;&lt;/span&gt;&lt;span style="font-style: normal;" class="ED-lem-sep"&gt; ] &lt;/span&gt;gemeint: &lt;span class="ED-name"&gt;Friedrich Alfred Schmid&lt;/span&gt; [Noerr] (1877–1969, zum Namenszusatz als Schriftsteller (nach einer Konditorei in Schmids Verwandschaft) &lt;abbr title="vergleiche" class="ED-abbr"&gt;vgl.&lt;/abbr&gt; Hermann Glockner: Heidelberger Bilderbuch. Erinnerungen. Bonn: Bouvier 1969, &lt;abbr title="Seite" class="ED-abbr"&gt;S.&lt;/abbr&gt; 50) mit dessen Freiburger Dissertation über Die Philosophie Fichtes mit Rücksicht auf die Frage nach der „Veränderten Lehre“, 1904 (im Buchhandel als: Fichtes Philosophie und das Problem ihrer inneren Einheit. (Die Frage nach der veränderten Lehre). Freiburg &lt;abbr title="im Breisgau" class="ED-abbr"&gt;i. B.&lt;/abbr&gt;: Ragoczy 1904; beide im Umfang von 112 &lt;abbr title="Seite" class="ED-abbr"&gt;S.&lt;/abbr&gt;). 1905 in Heidelberg habilitiert, dort bis 1917 &lt;abbr title="Privatdozent" class="ED-abbr"&gt;PD&lt;/abbr&gt; (1910–1917 &lt;abbr class="ED-abbr"&gt;a. o. Prof.&lt;/abbr&gt; für Philosophie und Ästhetik), danach freier Schriftsteller (Universität Heidelberg, Adreßbücher und Vorlesungsverzeichnisse: &lt;span class="ED-link"&gt;&lt;a href="http://www.ub.uni-heidelberg.de/helios/digi/quellenunihd.html"&gt;http://www.ub.uni-heidelberg.de/helios/digi/quellenunihd.html&lt;/a&gt;&lt;/span&gt;; Wikipedia 10.4.2017).&lt;/div&gt;&lt;div style="position: relative; margin: .3em 0em; margin-left: 2.5em; font-style: italic;" class="ED-app-editorial" id="app-editorial-4"&gt;&lt;span style="left: -2.5em; position: absolute; text-indent: 0em; font-style: normal;" class="ED-app-num"&gt;4&lt;/span&gt;&lt;a style="left: -.8em; position: absolute; text-indent: 0em; font-style: normal;" href="#app-editorial-4-ref" class="ED-app-corresp" title="back to content"&gt;↑&lt;/a&gt;&lt;span style="font-style: normal;" class="ED-lem"&gt;dem mir zugesicherten Seminar&lt;/span&gt;&lt;span style="font-style: normal;" class="ED-lem-sep"&gt; ] &lt;/span&gt;&lt;abbr title="vergleiche" class="ED-abbr"&gt;vgl.&lt;/abbr&gt; Windelband an &lt;span class="ED-name"&gt;Franz Böhm&lt;/span&gt; vom 22.2.1904 &lt;abbr title="folgende" class="ED-abbr"&gt;ff.&lt;/abbr&gt;&lt;/div&gt;&lt;div style="position: relative; margin: .3em 0em; margin-left: 2.5em; font-style: italic;" class="ED-app-editorial" id="app-editorial-5"&gt;&lt;span style="left: -2.5em; position: absolute; text-indent: 0em; font-style: normal;" class="ED-app-num"&gt;5&lt;/span&gt;&lt;a style="left: -.8em; position: absolute; text-indent: 0em; font-style: normal;" href="#app-editorial-5-ref" class="ED-app-corresp" title="back to content"&gt;↑&lt;/a&gt;&lt;span style="font-style: normal;" class="ED-lem"&gt;Artikel&lt;/span&gt;&lt;span style="font-style: normal;" class="ED-lem-sep"&gt; ] &lt;/span&gt;&lt;abbr title="vergleiche" class="ED-abbr"&gt;vgl.&lt;/abbr&gt; Windelband: Nach hundert Jahren. In: Kant-Studien 9 (1904), &lt;abbr title="Seite" class="ED-abbr"&gt;S.&lt;/abbr&gt; 5–20, sowie in: Zu Kants Gedächtnis. Zwölf Festgaben zu seinem 100jährigen Todestage. &lt;abbr title="Herausgeber" class="ED-abbr"&gt;Hg.&lt;/abbr&gt; &lt;abbr title="von" class="ED-abbr"&gt;v.&lt;/abbr&gt; H. Vaihinger &lt;abbr title="und" class="ED-abbr"&gt;u.&lt;/abbr&gt; B. Bauch.&lt;/div&gt;&lt;div style="position: relative; margin: .3em 0em; margin-left: 2.5em; font-style: italic;" class="ED-app-editorial" id="app-editorial-6"&gt;&lt;span style="left: -2.5em; position: absolute; text-indent: 0em; font-style: normal;" class="ED-app-num"&gt;6&lt;/span&gt;&lt;a style="left: -.8em; position: absolute; text-indent: 0em; font-style: normal;" href="#app-editorial-6-ref" class="ED-app-corresp" title="back to content"&gt;↑&lt;/a&gt;&lt;span style="font-style: normal;" class="ED-lem"&gt;&lt;span style="font-style: normal;" class="ED-lem"&gt;am 12 Februar&lt;/span&gt;&lt;/span&gt;&lt;span style="font-style: normal;" class="ED-lem-sep"&gt; ] &lt;/span&gt; abends 7 Uhr, zum 100. Todestag Kants, &lt;abbr title="vergleiche" class="ED-abbr"&gt;vgl.&lt;/abbr&gt; die Ankündigung in: Heidelberger Zeitung, &lt;abbr title="Nummer" class="ED-abbr"&gt;Nr.&lt;/abbr&gt; 25 vom 30.1.1904, Erstes Blatt, &lt;abbr title="Seite" class="ED-abbr"&gt;S.&lt;/abbr&gt; 4.&lt;/div&gt;&lt;div style="position: relative; margin: .3em 0em; margin-left: 2.5em; font-style: italic;" class="ED-app-editorial" id="app-editorial-7"&gt;&lt;span style="left: -2.5em; position: absolute; text-indent: 0em; font-style: normal;" class="ED-app-num"&gt;7&lt;/span&gt;&lt;a style="left: -.8em; position: absolute; text-indent: 0em; font-style: normal;" href="#app-editorial-7-ref" class="ED-app-corresp" title="back to content"&gt;↑&lt;/a&gt;&lt;span style="font-style: normal;" class="ED-lem"&gt;Festrede&lt;/span&gt;&lt;span style="font-style: normal;" class="ED-lem-sep"&gt; ] &lt;/span&gt;&lt;abbr title="vergleiche" class="ED-abbr"&gt;vgl.&lt;/abbr&gt; Windelband: Immanuel Kant und seine Weltanschauung. Gedenkrede zur Feier der 100. Wiederkehr seines Todestages, an der Universität Heidelberg. Heidelberg: C. Winter 1904.Berlin: Reuther &amp; Reichard 1904, &lt;abbr title="Seite" class="ED-abbr"&gt;S.&lt;/abbr&gt; 5–20.&lt;/div&gt;&lt;div style="position: relative; margin: .3em 0em; margin-left: 2.5em; font-style: italic;" class="ED-app-editorial" id="app-editorial-8"&gt;&lt;span style="left: -2.5em; position: absolute; text-indent: 0em; font-style: normal;" class="ED-app-num"&gt;8&lt;/span&gt;&lt;a style="left: -.8em; position: absolute; text-indent: 0em; font-style: normal;" href="#app-editorial-8-ref" class="ED-app-corresp" title="back to content"&gt;↑&lt;/a&gt;&lt;span style="font-style: normal;" class="ED-lem"&gt;unsre Universität in Stuttgart zu vertreten&lt;/span&gt;&lt;span style="font-style: normal;" class="ED-lem-sep"&gt; ] &lt;/span&gt;&lt;abbr title="vergleiche" class="ED-abbr"&gt;vgl.&lt;/abbr&gt; den Bericht in: Chronik der Stadt Heidelberg für das Jahr 1904. 12. &lt;abbr title="Jahrgang" class="ED-abbr"&gt;Jg.&lt;/abbr&gt;, im Auftrag des Stadtrates bearbeitet &lt;abbr title="von" class="ED-abbr"&gt;v.&lt;/abbr&gt; August Thorbecke. Heidelberg: I. Hörning 1906, &lt;abbr title="Seite" class="ED-abbr"&gt;S.&lt;/abbr&gt; 68:&lt;span style="font-style: normal;" class="ED-rdg"&gt; Als am 29. Januar Professor Dr. Ed. Zeller in Stuttgart seinen 90. Geburtstag feierte, überbrachte Geheimerat Dr. Windelband die Glückwünsche der Universität, deren Lehrer Zeller von 1862–1872 gewesen war; am 12. Februar, dem 100. Todestag Kants, feierte sie das Andenken an den großen Philosophen durch einen Festakt, bei dem Geheimerat Dr. Windelband die Festrede hielt. &lt;/span&gt;Die Stuttgarter Ansprache Windelbands ist abgedruckt in: Vom neunzigsten Geburtstag Eduard Zellers 22. Januar 1904. Als Manuscript gedruckt Stuttgart: Felix Krais 1904, &lt;abbr title="Seite" class="ED-abbr"&gt;S.&lt;/abbr&gt; 13–15: &lt;span style="font-style: normal;" class="ED-rdg"&gt;Exzellenz, ich komme im Namen von Heidelberg. Der engere Senat als Vertreter der Universität und die philosophische Fakultät haben mich gleichmäßig durch den Auftrag geehrt, Ihnen an diesem Tage, der seinesgleichen nicht in der gelehrten Welt hat, die ehrfurchtsvollsten Glückwünsche darzubringen. Das Jahrzehnt, das Sie in Ihrem an Arbeit und Erfolg reichen Leben unserer Universität gewidmet haben, steht bei uns in dankbarem Gedenken, wenn auch unter den jetzigen Mitgliedern der philosophischen Fakultät keiner mehr ist, der die Ehre hatte, mit Ew. Exzellenz zusammenwirken: unser Senior ist Ihr Nachfolger im Lehramt, Exzellenz Kuno Fischer. Er würde gewiß als Ihr treuer Verehrer und Freund am liebsten heute an dieser Stelle stehen, wenn ihn nicht die beklagenswerte Ungunst seines körperlichen Befindens daran hinderte, die ihn in diesem Semester auch gezwungen hat, auf sein Liebstes, die Lehrtätigkeit, zu verzichten. So ist es mir, der ich berufen sein werde, die Tradition der philosophischen Lehre an unserer Universität fortzusetzen, | die Sie, Exzellenz, geschaffen haben und die Kuno Fischer aufrecht erhalten hat – so ist es mir zugefallen, heute bei Ihnen unsre Universität zu vertreten; und ich weiß es meinen Herrn Kollegen innigen Dank, daß sie mir so die Gelegenheit gegeben haben, Ihnen auch persönlich die Gefühle auszudrücken, mit denen ich diesen Tag begrüße. Sie haben, Exzellenz, der Nestor der deutschen Philosophie, die Generationen kommen und gehen sehen. Sie sind erwachsen mit der Hochflut der idealistischen Spekulation und haben, als sie an den religiösen Fragen auseinander ging, in jungen Jahren Ihr gewichtiges Wort in den Streit geworfen. Sie haben dann über die Zeit der Ebbe des philosophischen Interesses, die auf so viel Ueberschwang folgen mußte, Ihr Schiff mit wertvollem Inhalt sicher gesteuert; in Hegels historischer Leistung fanden Sie den bleibenden Wert seines Wirkens, und die Kühnheiten seiner Konstruktion korrigierten Sie durch die bewundernswerte Weite und Breite Ihrer Gelehrsamkeit ebenso wie durch die strenge Sicherheit Ihres forschenden Wirklichkeitssinnes. An dem würdigsten Gegenstande, an der Philosophie, deren Schüler wir immer alle bleiben, bewährten Sie diese vorbildliche Kraft Ihres Geistes und schufen daraus das Werk, das monumentale, das mit Ihrem Namen die Zeiten überdauern wird. Allein niemals sind Sie der trüben Meinung gewesen, daß die Philosophie aufhören solle und nur ihre Geschichte übrig bleibe. Sie waren einer der Ersten, die zu der Besonnenheit des kritischen Philosophierens zurückriefen und einem philosophielosen Geschlechte lehrten, was Kant ihm wieder werden sollte. Aber auch dabei bewahrte Sie ihr historisches Verständnis und Ihr eignes fachliches Denken davor, bei der Aengstlichkeit der kantischen Erkenntnistheorie stehen zu bleiben, und so waren Sie es, der von Anfang an zur Arbeit an der objektiven Ausgestaltung seiner Lehre aufrief und führend anleitete, die in den letzten Jahrzehnten siegreich vorgedrungen ist. So sind wir alle historisch und systematisch Ihre Schüler und Sie genießen die Freude, alle Keime, die Sie ausgesät haben, als lebenskräftige Triebe sich entfalten zu sehen. Und so gestatten Sie auch mir, daß ich die Gunst des Tages, der mich | persönlich zu Ihnen führt, auszunutzen wage, um Ihnen auszusprechen, wie auch ich allzeit bewundernd zu Ihnen aufgeschaut habe und Ihrer Führung gefolgt bin. Mit meinen Kollegen, mit der ganzen wissenschaftlichen Welt preise ich die Gunst des Geschicks, das Sie uns in einer unvergleichlichen Rüstigkeit der geistigen Arbeit bis auf den heutigen Tag erhalten hat, und ich kann nichts besseres wünschen, als daß es Ihnen noch weiterhin lange gegeben sei, aus Ihrer schaffensreichen und gedankenvollen Muße heraus uns den Mitgenuß an den Früchten eines unermüdlichen Forschens zu gönnen. Der Wiederhall dessen, was Sie uns gelehrt haben und noch lehren, klingt allüberall: mögen Sie überzeugt sein, daß es nirgends freudiger aufgenommen und treuer bewahrt wird als in Heidelberg.&lt;/span&gt;&lt;/div&gt;&lt;div style="position: relative; margin: .3em 0em; margin-left: 2.5em; font-style: italic;" class="ED-app-editorial" id="app-editorial-9"&gt;&lt;span style="left: -2.5em; position: absolute; text-indent: 0em; font-style: normal;" class="ED-app-num"&gt;9&lt;/span&gt;&lt;a style="left: -.8em; position: absolute; text-indent: 0em; font-style: normal;" href="#app-editorial-9-ref" class="ED-app-corresp" title="back to content"&gt;↑&lt;/a&gt;&lt;span style="font-style: normal;" class="ED-lem"&gt;Ausgabe der Urteilskraft&lt;/span&gt;&lt;span style="font-style: normal;" class="ED-lem-sep"&gt; ] &lt;/span&gt;&lt;abbr class="ED-abbr"&gt;vgl&lt;/abbr&gt;. Windelband an Wilhelm Dilthey vom 16.7.1902 sowie Windelband: Einleitung. Sachliche Erläuterungen. Lesarten [zur Kritik der Urteilskraft]. In: Kant’s Werke &lt;abbr title="Band" class="ED-abbr"&gt;Bd.&lt;/abbr&gt; 5. Kritik der praktischen Vernunft. &lt;abbr title="Herausgeber" class="ED-abbr"&gt;Hg.&lt;/abbr&gt; &lt;abbr title="von" class="ED-abbr"&gt;v.&lt;/abbr&gt; Paul Natorp. Kritik der Urtheilskraft. &lt;abbr title="Herausgeber" class="ED-abbr"&gt;Hg.&lt;/abbr&gt; &lt;abbr title="von" class="ED-abbr"&gt;v.&lt;/abbr&gt; W. Windelband. Berlin: Georg Reimer 1908 (Kant’s Gesammelte Schriften. Hg. v. der Königlich Preußischen Akademie der Wissenschaften. &lt;abbr title="Abteilung" class="ED-abbr"&gt;Abt.&lt;/abbr&gt; 1, &lt;abbr title="Band" class="ED-abbr"&gt;Bd.&lt;/abbr&gt; 5), &lt;abbr title="Seite" class="ED-abbr"&gt;S.&lt;/abbr&gt; 512–527, 527–530, 530–543. 2. Abdruck Berlin: Georg Reimer 1913.&lt;/div&gt;&lt;/div&gt;</dc:description>
          <dc:subject>Wilhelm Windelband</dc:subject>
          <dc:subject>100 Philosophie und Psychologie » 100 Philosophie » 100 Philosophie und Psychologie</dc:subject>
          <dc:subject>Editionen » Wilhelm Windelband</dc:subject>
          <dc:type>Sammlungen, Datenmaterial » Editionen</dc:type>
          <dc:language>deu</dc:language>
          <dc:format>text/html</dc:format>
          <dc:format>application/pdf</dc:format>
          <dc:format>text/xml</dc:format>
          <dc:type>Text</dc:type>
        </oai_dc:dc>