<oai_dc:dc xmlns:oai_dc="http://www.openarchives.org/OAI/2.0/oai_dc/" xmlns:dc="http://purl.org/dc/elements/1.1/" xsi:schemaLocation="http://www.openarchives.org/OAI/2.0/oai_dc/  http://www.openarchives.org/OAI/2.0/oai_dc.xsd"  xmlns:xsi="http://www.w3.org/2001/XMLSchema-instance"><id>oai:elpub.bib.uni-wuppertal.de:14464</id><datestamp>2021-06-29</datestamp><setSpec>DDC:1:10:100</setSpec>
          <dc:title xml:lang="de">Forschungsgrundlagen Wilhelm Windelband&lt;br /&gt;&lt;br /&gt;Windelband an Georg Jellinek, Heidelberg, 20.9.1906, 1 S., hs. (lat. Schrift), Postkarte an Herrn GehHfr ProfDr Jellinek | hier | Bunsenstraße 15, mit Poststempel HEIDELBERG | 20.9.06 10–11 N | *1 h, Bundesarchiv Koblenz, Nachlass Georg Jellinek, N 1136/32</dc:title>
          <dc:creator>Bohr, Jörn</dc:creator>
          <dc:creator>Hartung, Gerald</dc:creator>
          <dc:creator>Bülow, Gilles</dc:creator>
          <dc:creator>Schlupkothen, Frederik</dc:creator>
          <dc:date>2021-06-21</dc:date>
          <dc:identifier>http://elpub.bib.uni-wuppertal.de/edocs/dokumente/edition/ww2020/0464</dc:identifier>
          <dc:identifier>http://elpub.bib.uni-wuppertal.de/servlets/DocumentServlet?id=14464</dc:identifier>
          <dc:identifier>urn:nbn:de:hbz:468-edww2020-000464-6</dc:identifier>
          <dc:identifier>http://elpub.bib.uni-wuppertal.de/servlets/DerivateServlet/Derivate-13464/</dc:identifier>
          <dc:description xml:lang="de">&lt;div xmlns="http://www.w3.org/1999/xhtml" style="font-family: serif; line-height: 1.2em; margin-bottom: 5em;" class="ED-TEI"&gt;&lt;p style="font-size: 1.1em; font-family: serif; font-style: italic; font-weight: normal; margin: 2em 0em 1em;" class="ED-titleStmt"&gt;Windelband an &lt;span class="ED-persName-received"&gt;Georg Jellinek&lt;/span&gt;, &lt;span class="ED-location-sent"&gt;Heidelberg&lt;/span&gt;, &lt;span class="ED-date"&gt;20.9.1906&lt;/span&gt;, &lt;span class="ED-note"&gt;1 S., hs. (lat. Schrift), Postkarte an&lt;/span&gt; &lt;span style="font-style: normal;" class="ED-rdg"&gt;Herrn GehHfr ProfDr Jellinek | hier | Bunsenstraße 15&lt;/span&gt;, &lt;span class="ED-note"&gt;mit Poststempel&lt;/span&gt; &lt;span style="font-style: normal;" class="ED-rdg"&gt;HEIDELBERG | 20.9.06 10–11 N | *1 h&lt;/span&gt;, &lt;span class="ED-pubPlace"&gt;Bundesarchiv Koblenz, Nachlass Georg Jellinek, N 1136/32&lt;/span&gt;&lt;/p&gt;&lt;div style="border: 1px solid LightGray; padding: 1em;" class="ED-text"&gt;&lt;p style="text-align: right; margin: 0em; margin-top: 1em;" class="ED-dateline"&gt;H&lt;span style="color: Gray;" class="ED-add"&gt;[eidelberg]&lt;/span&gt; 20.9.06&lt;/p&gt;&lt;p style="text-indent: 0em; margin: 0em; margin-top: 1em;" class="ED-salute"&gt;Lieber Freund,&lt;/p&gt;&lt;p style="text-indent: 0em; margin: 0em; margin-top: 1em;" class="ED-p"&gt;Meine Frau u&lt;span style="color: Gray;" class="ED-add"&gt;[nd]&lt;/span&gt; ich bitten also Dich und, wenn es ihm irgend Freude macht, auch &lt;span style="text-decoration: underline dotted;" class="ED-text-lem" itemref="app-editorial-1" title="Deinen Bruder ] welcher der beiden Brüder Georg Jellineks (Emil Jellinek-Mercédès (1853–1918), Max Hermann Jellinek (1868–1938), NDB) gemeint ist, ist nicht ermittelt."&gt;Deinen Bruder&lt;/span&gt;&lt;a style="font-style: normal; vertical-align: super; font-size: 80%; line-height: 100%;" class="ED-anchor" href="#app-editorial-1" id="app-editorial-1-ref" title="Deinen Bruder ] welcher der beiden Brüder Georg Jellineks (Emil Jellinek-Mercédès (1853–1918), Max Hermann Jellinek (1868–1938), NDB) gemeint ist, ist nicht ermittelt."&gt;[1]&lt;/a&gt;, morgen Abend 18 Uhr mit &lt;span class="ED-name"&gt;Hensel&lt;/span&gt; bei uns zu essen: wir haben nur noch &lt;span class="ED-name"&gt;Troeltsch&lt;/span&gt; und &lt;span class="ED-name"&gt;&lt;span style="text-decoration: underline dotted;" class="ED-text-lem" itemref="app-editorial-2" title="Petsch ] Robert Petsch (1875–1945), Germanist, 1904–1911 ao. Prof. Heidelberg, seit 1911 in Liverpool (WBIS)."&gt;Petsch&lt;/span&gt;&lt;/span&gt;&lt;span class="ED-name"&gt;&lt;a style="font-style: normal; vertical-align: super; font-size: 80%; line-height: 100%;" class="ED-anchor" href="#app-editorial-2" id="app-editorial-2-ref" title="Petsch ] Robert Petsch (1875–1945), Germanist, 1904–1911 ao. Prof. Heidelberg, seit 1911 in Liverpool (WBIS)."&gt;[2]&lt;/a&gt;&lt;/span&gt; dazu gebeten, und bei &lt;span class="ED-name"&gt;Hensel&lt;/span&gt; angefragt, ob er noch den einen oder den andern Herrn dazu geladen wünsche.&lt;/p&gt;&lt;p style="text-indent: 1em; margin: 0em;" class="ED-p"&gt;Ausbleiben der Antwort gilt als Annahme.&lt;/p&gt;&lt;p style="text-indent: 1em; margin: 0em;" class="ED-p"&gt;Mit herzlichen Gruss Dein&lt;/p&gt;&lt;p style="text-indent: 0em; margin: 0em; margin-top: 1em;" class="ED-signed"&gt;WWd.&lt;/p&gt;&lt;/div&gt;&lt;h2 style="font-size: 1.1em; font-family: serif; font-style: italic; font-weight: normal; margin: 2em 0em 1em;" class="ED-app-title"&gt;Anmerkungen der Herausgeber&lt;/h2&gt;&lt;div style="position: relative; margin: .3em 0em; margin-left: 2.5em; font-style: italic;" class="ED-app-editorial" id="app-editorial-1"&gt;&lt;span style="left: -2.5em; position: absolute; text-indent: 0em; font-style: normal;" class="ED-app-num"&gt;1&lt;/span&gt;&lt;a style="left: -.8em; position: absolute; text-indent: 0em; font-style: normal;" href="#app-editorial-1-ref" class="ED-app-corresp" title="back to content"&gt;↑&lt;/a&gt;&lt;span style="font-style: normal;" class="ED-lem"&gt;Deinen Bruder&lt;/span&gt;&lt;span style="font-style: normal;" class="ED-lem-sep"&gt; ] &lt;/span&gt;welcher der beiden Brüder &lt;span class="ED-name"&gt;Georg Jellinek&lt;/span&gt;s (&lt;span class="ED-name"&gt;Emil Jellinek-Mercédès&lt;/span&gt; (1853–1918), &lt;span class="ED-name"&gt;Max Hermann Jellinek&lt;/span&gt; (1868–1938), &lt;abbr title="Neue Deutsche Biographie" class="ED-abbr"&gt;NDB&lt;/abbr&gt;) gemeint ist, ist nicht ermittelt.&lt;/div&gt;&lt;div style="position: relative; margin: .3em 0em; margin-left: 2.5em; font-style: italic;" class="ED-app-editorial" id="app-editorial-2"&gt;&lt;span style="left: -2.5em; position: absolute; text-indent: 0em; font-style: normal;" class="ED-app-num"&gt;2&lt;/span&gt;&lt;a style="left: -.8em; position: absolute; text-indent: 0em; font-style: normal;" href="#app-editorial-2-ref" class="ED-app-corresp" title="back to content"&gt;↑&lt;/a&gt;&lt;span style="font-style: normal;" class="ED-lem"&gt;&lt;span class="ED-name"&gt;Petsch&lt;/span&gt;&lt;/span&gt;&lt;span style="font-style: normal;" class="ED-lem-sep"&gt; ] &lt;/span&gt;&lt;span class="ED-name"&gt;Robert Petsch&lt;/span&gt; (1875–1945), Germanist, 1904–1911 &lt;abbr title="außerordentlicher Professor" class="ED-abbr"&gt;ao. Prof.&lt;/abbr&gt; Heidelberg, seit 1911 in Liverpool (&lt;abbr title="World Biographical Information System" class="ED-abbr"&gt;WBIS&lt;/abbr&gt;).&lt;/div&gt;&lt;/div&gt;</dc:description>
          <dc:subject>Wilhelm Windelband</dc:subject>
          <dc:subject>100 Philosophie und Psychologie » 100 Philosophie » 100 Philosophie und Psychologie</dc:subject>
          <dc:subject>Editionen » Wilhelm Windelband</dc:subject>
          <dc:type>Sammlungen, Datenmaterial » Editionen</dc:type>
          <dc:language>deu</dc:language>
          <dc:format>text/html</dc:format>
          <dc:format>application/pdf</dc:format>
          <dc:format>text/xml</dc:format>
          <dc:type>Text</dc:type>
        </oai_dc:dc>