<oai_dc:dc xmlns:oai_dc="http://www.openarchives.org/OAI/2.0/oai_dc/" xmlns:dc="http://purl.org/dc/elements/1.1/" xsi:schemaLocation="http://www.openarchives.org/OAI/2.0/oai_dc/  http://www.openarchives.org/OAI/2.0/oai_dc.xsd"  xmlns:xsi="http://www.w3.org/2001/XMLSchema-instance"><id>oai:elpub.bib.uni-wuppertal.de:4340</id><datestamp>2018-01-22</datestamp><setSpec>DDC:5:53</setSpec>
          <dc:title xml:lang="en">Perturbative Calculations and Their Application to Higgs Physics</dc:title>
          <dc:creator>Zirke, Tom J. E.</dc:creator>
          <dc:date>2018-01-22</dc:date>
          <dc:identifier>http://elpub.bib.uni-wuppertal.de/edocs/dokumente/fbc/physik/diss2014/zirke</dc:identifier>
          <dc:identifier>http://elpub.bib.uni-wuppertal.de/servlets/DocumentServlet?id=4340</dc:identifier>
          <dc:identifier>urn:nbn:de:hbz:468-20141111-110606-0</dc:identifier>
          <dc:identifier>http://elpub.bib.uni-wuppertal.de/servlets/DerivateServlet/Derivate-4329/dc1424.pdf</dc:identifier>
          <dc:subject>500 Naturwissenschaften und Mathematik » 530 Physik</dc:subject>
          <dc:subject>Fakultät für Mathematik und Naturwissenschaften » Physik » Dissertationen</dc:subject>
          <dc:type>Wissenschaftliche Abschlussarbeiten » Dissertation</dc:type>
          <dc:language>eng</dc:language>
          <dc:format>application/pdf</dc:format>
          <dc:type>Text</dc:type>
        </oai_dc:dc>